astsadata/__init__.py
astsadata/astsadata.py
astsadata/data/EQ5.csv
astsadata/data/EQcount.csv
astsadata/data/EXP6.csv
astsadata/data/HCT.csv
astsadata/data/Hare.csv
astsadata/data/Lynx.csv
astsadata/data/PLT.csv
astsadata/data/UnempRate.csv
astsadata/data/WBC.csv
astsadata/data/ar1miss.csv
astsadata/data/arf.csv
astsadata/data/beamd.csv
astsadata/data/birth.csv
astsadata/data/blood.csv
astsadata/data/bnrf1ebv.csv
astsadata/data/bnrf1hvs.csv
astsadata/data/cardox.csv
astsadata/data/chicken.csv
astsadata/data/climhyd.csv
astsadata/data/cmort.csv
astsadata/data/cpg.csv
astsadata/data/djia.csv
astsadata/data/econ5.csv
astsadata/data/eqexp.csv
astsadata/data/flu.csv
astsadata/data/fmri1.csv
astsadata/data/gas.csv
astsadata/data/gdp.csv
astsadata/data/globtemp.csv
astsadata/data/globtempl.csv
astsadata/data/gnp.csv
astsadata/data/gtemp.csv
astsadata/data/gtemp2.csv
astsadata/data/gtemp_land.csv
astsadata/data/gtemp_ocean.csv
astsadata/data/hor.csv
astsadata/data/jj.csv
astsadata/data/lap.csv
astsadata/data/lead.csv
astsadata/data/nyse.csv
astsadata/data/oil.csv
astsadata/data/part.csv
astsadata/data/polio.csv
astsadata/data/prodn.csv
astsadata/data/qinfl.csv
astsadata/data/qintr.csv
astsadata/data/rec.csv
astsadata/data/sales.csv
astsadata/data/salmon.csv
astsadata/data/salt.csv
astsadata/data/saltemp.csv
astsadata/data/so2.csv
astsadata/data/soi.csv
astsadata/data/soiltemp.csv
astsadata/data/speech.csv
astsadata/data/star.csv
astsadata/data/sunspotz.csv
astsadata/data/tempr.csv
astsadata/data/unemp.csv
astsadata/data/varve.csv
astsadata-0.0.4.dist-info/LICENSE
astsadata-0.0.4.dist-info/METADATA
astsadata-0.0.4.dist-info/WHEEL
astsadata-0.0.4.dist-info/top_level.txt
astsadata-0.0.4.dist-info/RECORD
