Metadata-Version: 2.1
Name: astsadata
Version: 0.0.4
Summary: Python package that contains all datasets from R astsa package
Home-page: https://github.com/evorition/astsadata
Author: Maxim Makovskiy
Author-email: makovskiyms@gmail.com
License: GPLv3
Platform: UNKNOWN
Classifier: Programming Language :: Python :: 3
Classifier: License :: OSI Approved :: GNU General Public License v3 (GPLv3)
Requires-Python: >=3.6
Requires-Dist: pandas
